odoo/addons/pos_ticket_static_qrcode/README.rst
odoo/addons/pos_ticket_static_qrcode/__init__.py
odoo/addons/pos_ticket_static_qrcode/__manifest__.py
odoo/addons/pos_ticket_static_qrcode/i18n/fr.po
odoo/addons/pos_ticket_static_qrcode/i18n/it.po
odoo/addons/pos_ticket_static_qrcode/i18n/pos_ticket_qrcode.pot
odoo/addons/pos_ticket_static_qrcode/i18n/pos_ticket_static_qrcode.pot
odoo/addons/pos_ticket_static_qrcode/models/__init__.py
odoo/addons/pos_ticket_static_qrcode/models/pos_config.py
odoo/addons/pos_ticket_static_qrcode/readme/CONFIGURE.rst
odoo/addons/pos_ticket_static_qrcode/readme/CONTRIBUTORS.rst
odoo/addons/pos_ticket_static_qrcode/readme/DESCRIPTION.rst
odoo/addons/pos_ticket_static_qrcode/readme/USAGE.rst
odoo/addons/pos_ticket_static_qrcode/static/description/icon.png
odoo/addons/pos_ticket_static_qrcode/static/description/index.html
odoo/addons/pos_ticket_static_qrcode/static/description/pos_ticket.png
odoo/addons/pos_ticket_static_qrcode/static/src/xml/pos.xml
odoo/addons/pos_ticket_static_qrcode/tests/__init__.py
odoo/addons/pos_ticket_static_qrcode/tests/test_pos_config.py
odoo/addons/pos_ticket_static_qrcode/views/pos_config.xml
odoo12_addon_pos_ticket_static_qrcode-12.0.1.0.0.99.dev6.dist-info/METADATA
odoo12_addon_pos_ticket_static_qrcode-12.0.1.0.0.99.dev6.dist-info/WHEEL
odoo12_addon_pos_ticket_static_qrcode-12.0.1.0.0.99.dev6.dist-info/top_level.txt
odoo12_addon_pos_ticket_static_qrcode-12.0.1.0.0.99.dev6.dist-info/RECORD
